proxy_extractor/__init__.py
proxy_extractor/checker.py
proxy_extractor/extractor.py
proxy_extractor/requester.py
proxy_extractor/scraper.py
proxy_extractor/useragents.py
proxy_extractor-0.1.1.dist-info/LICENSE
proxy_extractor-0.1.1.dist-info/METADATA
proxy_extractor-0.1.1.dist-info/WHEEL
proxy_extractor-0.1.1.dist-info/top_level.txt
proxy_extractor-0.1.1.dist-info/RECORD
