Metadata-Version: 2.1
Name: proxy-extractor
Version: 0.1.1
Summary: Package to extract free proxies from various free proxy listings
Home-page: https://github.com/Ganofins/proxy-extractor
Author: Ganofins
Author-email: bagariaganesh@gmail.com
License: UNKNOWN
Platform: UNKNOWN
Classifier: Programming Language :: Python :: 3.5
Classifier: Programming Language :: Python :: 3.6
Classifier: Programming Language :: Python :: 3.7
Classifier: License :: OSI Approved :: MIT License
Classifier: Operating System :: OS Independent
Classifier: Topic :: Software Development :: Libraries :: Python Modules
